TracGoogleWebmasterVerifyPlugin-0.3.dist-info/METADATA
TracGoogleWebmasterVerifyPlugin-0.3.dist-info/RECORD
TracGoogleWebmasterVerifyPlugin-0.3.dist-info/WHEEL
TracGoogleWebmasterVerifyPlugin-0.3.dist-info/entry_points.txt
TracGoogleWebmasterVerifyPlugin-0.3.dist-info/top_level.txt
tracgooglewebmasterverify/__init__.py
tracgooglewebmasterverify/plugin.py
